goji/__init__.py
goji/__main__.py
goji/ansi.py
goji/auth.py
goji/client.py
goji/commands.py
goji/config.py
goji/models.py
goji/text_parser.py
goji/utils.py
goji-0.6.0.dist-info/LICENSE
goji-0.6.0.dist-info/METADATA
goji-0.6.0.dist-info/WHEEL
goji-0.6.0.dist-info/entry_points.txt
goji-0.6.0.dist-info/RECORD
