Metadata-Version: 2.1
Name: goji
Version: 0.6.0
Summary: Command line JIRA client
License: BSD
Author: Kyle Fuller
Author-email: kyle@fuller.li
Requires-Python: >=3.9,<4.0
Classifier: License :: Other/Proprietary License
Classifier: Programming Language :: Python :: 3
Classifier: Programming Language :: Python :: 3.9
Classifier: Programming Language :: Python :: 3.10
Classifier: Programming Language :: Python :: 3.11
Classifier: Programming Language :: Python :: 3.12
Classifier: Programming Language :: Python :: 3.13
Requires-Dist: click (>=8.1.8,<9.0.0)
Requires-Dist: jsonschema (>=4.23.0,<5.0.0)
Requires-Dist: requests[socks] (>=2.27.1,<3.0.0)
Requires-Dist: toml (>=0.10.2,<0.11.0)
